algos/__init__.py
algos/cpo.py
algos/dcpo.py
algos/policy_gradient_safe.py
algos/trpo_safe.py
envs/__init__.py
envs/inventory_management.py
envs/safe_env.py
envs/saute_env.py
evaluation/__init__.py
evaluation/evaluator.py
evaluation/plotter.py
evaluation/plotter_base.py
experiments/__init__.py
experiments/backlog.py
optimizers/__init__.py
optimizers/conjugate_constraint_optimizer.py
policies/__init__.py
policies/gaussian.py
policies/implicit.py
safety_constraints/__init__.py
safety_constraints/base.py
safety_constraints/inventory_constraint.py
sampler/__init__.py
sampler/safe_worker.py
sampler/sampler_safe.py
utils/__init__.py
utils/agent.py
utils/env.py
utils/eval.py
utils/math.py
utils/misc.py
value_functions/__init__.py
value_functions/gaussian.py
value_functions/modules.py
value_functions/quantile_regression.py
jaisalab-0.0.1.dist-info/METADATA
jaisalab-0.0.1.dist-info/WHEEL
jaisalab-0.0.1.dist-info/top_level.txt
jaisalab-0.0.1.dist-info/RECORD
