Metadata-Version: 2.1
Name: jaisalab
Version: 0.0.1
Summary: Framework that builds on the garage toolkit for the evaluation and                  development of constrained RL algorithms.
Home-page: https://github.com/jaimesabalimperial/jaisalab
Author: Jaime Sabal Bermúdez
Author-email: jsabalb@gmail.com
Classifier: Programming Language :: Python :: 3
Classifier: License :: OSI Approved :: MIT License
Classifier: Operating System :: OS Independent
Requires-Python: >=3.6
